odoo10_addon_account_voucher_operating_unit-10.0.1.0.0.99.dev3-py2.7-nspkg.pth
odoo/addons/account_voucher_operating_unit/README.rst
odoo/addons/account_voucher_operating_unit/__init__.py
odoo/addons/account_voucher_operating_unit/__manifest__.py
odoo/addons/account_voucher_operating_unit/models/__init__.py
odoo/addons/account_voucher_operating_unit/models/account_voucher.py
odoo/addons/account_voucher_operating_unit/security/account_voucher_security.xml
odoo/addons/account_voucher_operating_unit/static/description/icon.png
odoo/addons/account_voucher_operating_unit/tests/__init__.py
odoo/addons/account_voucher_operating_unit/tests/test_account_voucher_operating_unit.py
odoo/addons/account_voucher_operating_unit/tests/test_receipt_operating_unit.py
odoo/addons/account_voucher_operating_unit/views/account_voucher_sales_purchase_view.xml
odoo10_addon_account_voucher_operating_unit-10.0.1.0.0.99.dev3.dist-info/METADATA
odoo10_addon_account_voucher_operating_unit-10.0.1.0.0.99.dev3.dist-info/RECORD
odoo10_addon_account_voucher_operating_unit-10.0.1.0.0.99.dev3.dist-info/WHEEL
odoo10_addon_account_voucher_operating_unit-10.0.1.0.0.99.dev3.dist-info/namespace_packages.txt
odoo10_addon_account_voucher_operating_unit-10.0.1.0.0.99.dev3.dist-info/top_level.txt
